[
    {"name": "Classic White T-Shirt", "price": 12.99},
    {"name": "Slim Fit Jeans", "price": 39.99},
    {"name": "Hooded Sweatshirt", "price": 29.5},
    {"name": "Denim Jacket", "price": 54.0},
    {"name": "Leather Belt", "price": 18.75},
    {"name": "Casual Sneakers", "price": 49.99},
    {"name": "Wool Scarf", "price": 15.2},
    {"name": "Baseball Cap", "price": 11.0},
    {"name": "Formal Blazer", "price": 79.99},
    {"name": "Chino Shorts", "price": 24.99},
    {"name": "Polo Shirt", "price": 22.5},
    {"name": "Running Shoes", "price": 65.0},
    {"name": "Yoga Pants", "price": 27.99},
    {"name": "Tank Top", "price": 9.99},
    {"name": "Flannel Shirt", "price": 34.5},
    {"name": "Cargo Pants", "price": 42.0},
    {"name": "Beanie Hat", "price": 13.25},
    {"name": "Winter Coat", "price": 120.0},
    {"name": "Swim Trunks", "price": 19.99},
    {"name": "Leather Jacket", "price": 150.0},
    {"name": "Ankle Boots", "price": 68.75},
    {"name": "Graphic T-Shirt", "price": 14.99},
    {"name": "Pleated Skirt", "price": 31.0},
    {"name": "Maxi Dress", "price": 45.5},
    {"name": "Button-Up Shirt", "price": 28.99},
    {"name": "Cardigan Sweater", "price": 36.75}
  ]